attackai/__init__.py
attackai/attackai.py
attackai-1.0.0.dist-info/LICENSE.txt
attackai-1.0.0.dist-info/METADATA
attackai-1.0.0.dist-info/WHEEL
attackai-1.0.0.dist-info/top_level.txt
attackai-1.0.0.dist-info/RECORD
