Metadata-Version: 2.1
Name: attackai
Version: 1.0.0
Summary: Simulation of poisoning attack on AI model
Author: Dr. Deniz Dahman's
Author-email: dahmansphi@gmail.com
Project-URL: Source, https://github.com/dahmansphi/attackai
Project-URL: Project, https://dahmansphi.com/attackai
Keywords: Cybersecurity,Machine Learning,Artificial Intelligence,Poisoning attack
Classifier: Development Status :: 3 - Alpha
Classifier: Intended Audience :: Developers
Classifier: Topic :: Software Development :: Build Tools
Classifier: License :: OSI Approved :: MIT License
Classifier: Programming Language :: Python :: 3
Requires-Python: >=3.9
License-File: LICENSE.txt
